{"name":"Pyraft","tagline":"Reconstruction Algorithms for Tomography in Python","body":"RECONSTRUCTION ALGORITHMS FOR TOMOGRAPHY for Python\r\n----------------------------------------------------\r\n\r\nAuthors:\r\n\r\na) Eduardo X. Miqueles\t\tLNLS/CNPEM\r\nb) Elias S. Helou\t\tICMC/USP\r\nc) Nikolay Koshev\t\tLNLS/CNPEM\r\n\r\nContributors:\r\n\r\n- Rafael F.C Vescovi\t\tLNLS/CNPEM\r\n- João Carlos Cerqueira\t\tFEEC/UNICAMP\r\n- Hugo H. Slepicka\t\t\tBNL\r\n\r\n\r\n-----------------------------------------------------\r\nInstall:\r\n\r\nsudo -E python setup.py install\r\n\r\nUninstall\r\n\r\nsudo pip uninstall pyraft\r\n\r\n\r\n","google":"","note":"Don't delete this file! It's used internally to help with page regeneration."}